magen_datastore-1.0a1.dist-info/DESCRIPTION.rst
magen_datastore-1.0a1.dist-info/METADATA
magen_datastore-1.0a1.dist-info/RECORD
magen_datastore-1.0a1.dist-info/WHEEL
magen_datastore-1.0a1.dist-info/metadata.json
magen_datastore-1.0a1.dist-info/top_level.txt
magen_datastore_apis/__init__.py
magen_datastore_apis/dao_interface.py
magen_datastore_apis/main_db.py
magen_datastore_apis/utils_db.py
